{
  "data": [
    {
      "Date": "2025-10-03",
      "Ticker": "ES1!",
      "Call": 6848.9,
      "Put": 6548.9,
      "Vol": 6743.9,
      "Zero": 6748.9,
      "Gamma": 6048.9,
      "L2": 6798.9,
      "L3": 6698.9,
      "L4": 6851.9,
      "C1": 6797.9,
      "C2": 6770.9,
      "C3": 7045.9,
      "C4": 6674.9,
      "1Day": "0.61%",
      "5Day": "1.43%"
    },
    {
      "Date": "2025-10-02",
      "Ticker": "ES1!",
      "Call": 6799.2,
      "Put": 6549.2,
      "Vol": 6729.2,
      "Zero": 6749.2,
      "Gamma": 6049.2,
      "L2": 6799.2,
      "L3": 6699.2,
      "L4": 6800.2,
      "C1": 6787.2,
      "C2": 6847.2,
      "C3": 6774.2,
      "C4": 6671.2,
      "1Day": "0.61%",
      "5Day": "1.43%"
    },
    {
      "Date": "2025-10-01",
      "Ticker": "ES1!",
      "Call": 6751.85,
      "Put": 6551.85,
      "Vol": 6706.85,
      "Zero": 6751.85,
      "Gamma": 6051.85,
      "L2": 6701.85,
      "L3": 6651.85,
      "L4": 6753.85,
      "C1": 6800.85,
      "C2": 6853.85,
      "C3": 7054.85,
      "C4": 6650.85,
      "1Day": "0.61%",
      "5Day": "1.43%"
    },
    {
      "Date": "2025-09-30",
      "Ticker": "ES1!",
      "Call": 6752.65,
      "Put": 6552.65,
      "Vol": 6692.65,
      "Zero": 6752.65,
      "Gamma": 6702.65,
      "L2": 6052.65,
      "L3": 6652.65,
      "L4": 6753.65,
      "C1": 6800.65,
      "C2": 6853.65,
      "C3": 6780.65,
      "C4": 6674.65,
      "1Day": "0.62%",
      "5Day": "1.43%"
    },
    {
      "Date": "2025-09-29",
      "Ticker": "ES1!",
      "Call": 6752.65,
      "Put": 6662.65,
      "Vol": 6692.65,
      "Zero": 6052.65,
      "Gamma": 6752.65,
      "L2": 6652.65,
      "L3": 6702.65,
      "L4": 6749.65,
      "C1": 6855.65,
      "C2": 6729.65,
      "C3": 6629.65,
      "C4": 6657.65,
      "1Day": "0.62%",
      "5Day": "1.43%"
    },
    {
      "Date": "2025-09-26",
      "Ticker": "ES1!",
      "Call": 6755.35,
      "Put": 6555.35,
      "Vol": 6670.35,
      "Zero": 6655.35,
      "Gamma": 6055.35,
      "L2": 6555.35,
      "L3": 6705.35,
      "L4": 6752.35,
      "C1": 6858.35,
      "C2": 6554.35,
      "C3": 6633.35,
      "C4": 6621.35,
      "1Day": "0.60%",
      "5Day": "1.81%"
    },
    {
      "Date": "2025-09-25",
      "Ticker": "ES1!",
      "Call": 6755.58,
      "Put": 6555.58,
      "Vol": 6695.58,
      "Zero": 6055.58,
      "Gamma": 6655.58,
      "L2": 6755.58,
      "L3": 6705.58,
      "L4": 6753.58,
      "C1": 6633.58,
      "C2": 6852.58,
      "C3": 6806.58,
      "C4": 6654.58,
      "1Day": "0.63%",
      "5Day": "1.81%"
    },
    {
      "Date": "2025-09-24",
      "Ticker": "ES1!",
      "Call": 6756.26,
      "Put": 6556.26,
      "Vol": 6721.26,
      "Zero": 6056.26,
      "Gamma": 6756.26,
      "L2": 6656.26,
      "L3": 6706.26,
      "L4": 6753.26,
      "C1": 6853.26,
      "C2": 6633.26,
      "C3": 6806.26,
      "C4": 6674.26,
      "1Day": "0.63%",
      "5Day": "1.81%"
    },
    {
      "Date": "2025-09-23",
      "Ticker": "ES1!",
      "Call": 6757.52,
      "Put": 6557.52,
      "Vol": 6677.52,
      "Zero": 6757.52,
      "Gamma": 6057.52,
      "L2": 6657.52,
      "L3": 6707.52,
      "L4": 6757.52,
      "C1": 6784.52,
      "C2": 6804.52,
      "C3": 6858.52,
      "C4": 6662.52,
      "1Day": "0.63%",
      "5Day": "1.81%"
    },
    {
      "Date": "2025-09-22",
      "Ticker": "ES1!",
      "Call": 6758.7,
      "Put": 6458.7,
      "Vol": 6678.7,
      "Zero": 6058.7,
      "Gamma": 6758.7,
      "L2": 6658.7,
      "L3": 6708.7,
      "L4": 6762.7,
      "C1": 6862.7,
      "C2": 6782.7,
      "C3": 6809.7,
      "C4": 6634.7,
      "1Day": "0.60%",
      "5Day": "1.81%"
    },
    {
      "Date": "2025-09-19",
      "Ticker": "ES1!",
      "Call": 6710.18,
      "Put": 6460.18,
      "Vol": 6630.18,
      "Zero": 6710.18,
      "Gamma": 6660.18,
      "L2": 6060.18,
      "L3": 6560.18,
      "L4": 6712.18,
      "C1": 6758.18,
      "C2": 6732.18,
      "C3": 6858.18,
      "C4": 6604.18,
      "1Day": "0.61%",
      "5Day": "1.59%"
    },
    {
      "Date": "2025-09-18",
      "Ticker": "ES1!",
      "Call": 6710.77,
      "Put": 6360.77,
      "Vol": 6560.77,
      "Zero": 6660.77,
      "Gamma": 6710.77,
      "L2": 6560.77,
      "L3": 6060.77,
      "L4": 6713.77,
      "C1": 6759.77,
      "C2": 6660.77,
      "C3": 6687.77,
      "C4": 6572.77,
      "1Day": "0.59%",
      "5Day": "1.59%"
    },
    {
      "Date": "2025-09-17",
      "Ticker": "ES1!",
      "Call": 6761.6,
      "Put": 6361.6,
      "Vol": 6561.6,
      "Zero": 6661.6,
      "Gamma": 6561.6,
      "L2": 6061.6,
      "L3": 6711.6,
      "L4": 6714.6,
      "C1": 6760.6,
      "C2": 6661.6,
      "C3": 6859.6,
      "C4": 6580.6,
      "1Day": "0.57%",
      "5Day": "1.59%"
    },
    {
      "Date": "2025-09-16",
      "Ticker": "ES1!",
      "Call": 6711.8,
      "Put": 6361.8,
      "Vol": 6556.8,
      "Zero": 6661.8,
      "Gamma": 6561.8,
      "L2": 6061.8,
      "L3": 6611.8,
      "L4": 6709.8,
      "C1": 6762.8,
      "C2": 6683.8,
      "C3": 6663.8,
      "C4": 6588.8,
      "1Day": "0.58%",
      "5Day": "1.59%"
    },
    {
      "Date": "2025-09-15",
      "Ticker": "ES1!",
      "Call": 6659.14,
      "Put": 6359.14,
      "Vol": 6554.14,
      "Zero": 6559.14,
      "Gamma": 6659.14,
      "L2": 6059.14,
      "L3": 6609.14,
      "L4": 6656.14,
      "C1": 6709.14,
      "C2": 6676.14,
      "C3": 6762.14,
      "C4": 6556.14,
      "1Day": "0.58%",
      "5Day": "1.59%"
    },
    {
      "Date": "2025-09-12",
      "Ticker": "ES1!",
      "Call": 6606.96,
      "Put": 6306.96,
      "Vol": 6501.96,
      "Zero": 6506.96,
      "Gamma": 6606.96,
      "L2": 6006.96,
      "L3": 6556.96,
      "L4": 6607.96,
      "C1": 6653.96,
      "C2": 6633.96,
      "C3": 6705.96,
      "C4": 6457.96,
      "1Day": "0.58%",
      "5Day": "1.76%"
    }
  ]
}